mochikernel/__init__.py
mochikernel/__main__.py
mochikernel/mochikernel.py
mochikernel-0.2.2.dist-info/DESCRIPTION.rst
mochikernel-0.2.2.dist-info/METADATA
mochikernel-0.2.2.dist-info/metadata.json
mochikernel-0.2.2.dist-info/RECORD
mochikernel-0.2.2.dist-info/top_level.txt
mochikernel-0.2.2.dist-info/WHEEL
