Metadata-Version: 2.0
Name: mochikernel
Version: 0.2.2
Summary: An IPython kernel for Mochi
Home-page: https://github.com/Carreau/mochi-kernel
Author: Matthias Bussonnier, Mike Müller
Author-email: bussonniermatthias@gmail.com, pymmueller@gmail.com
License: BSD
Keywords: mochikernel
Platform: UNKNOWN
Classifier: Development Status :: 2 - Pre-Alpha
Classifier: Intended Audience :: Developers
Classifier: License :: OSI Approved :: BSD License
Classifier: Natural Language :: English
Classifier: Programming Language :: Python :: 3
Classifier: Programming Language :: Python :: 3.3
Classifier: Programming Language :: Python :: 3.4
